zcompy/__init__.py
zcompy/absl_command.py
zcompy/command.py
zcompy/fire_command.py
zcompy/option.py
zcompy/parser_command.py
zcompy/utils.py
zcompy/action/__init__.py
zcompy/action/action.py
zcompy/action/extend_action.py
zcompy-0.0.1.dist-info/licenses/LICENSE
zcompy-0.0.1.dist-info/METADATA
zcompy-0.0.1.dist-info/WHEEL
zcompy-0.0.1.dist-info/top_level.txt
zcompy-0.0.1.dist-info/RECORD
