Metadata-Version: 2.4
Name: zcompy
Version: 0.0.1
Summary: Generate zsh completions with Python.
Maintainer-email: Feng Wang <wangfeng19950315@163.com>
License:                                  Apache License
Project-URL: Homepage, https://github.com/FateScript/zcompy
Requires-Python: >=3.8
License-File: LICENSE
Provides-Extra: dev
Requires-Dist: absl-py; extra == "dev"
Requires-Dist: pytest; extra == "dev"
Requires-Dist: pytest-cov; extra == "dev"
Requires-Dist: ruff; extra == "dev"
Requires-Dist: toml; extra == "dev"
Requires-Dist: tox; extra == "dev"
Dynamic: license-file
